[
  {
    "name": "Онбординг",
    "slug": "onboarding",
    "description": "Материалы для адаптации новых сотрудников",
    "department": "Engineering",
    "position": "Software Engineer",
    "level": "JUNIOR",
    "order": 1,
    "icon": "book-open",
    "color": "#4CAF50"
  },
  {
    "name": "Разработка",
    "slug": "development",
    "description": "Гайды по разработке, инструменты и лучшие практики",
    "department": "Engineering",
    "position": "Software Engineer",
    "level": "JUNIOR",
    "order": 2,
    "icon": "code",
    "color": "#2196F3"
  },
  {
    "name": "Политики компании",
    "slug": "company-policies",
    "description": "HR политики, процедуры и соответствие",
    "department": "Operations",
    "position": "HR Specialist",
    "level": "JUNIOR",
    "order": 3,
    "icon": "shield-check",
    "color": "#FF9800"
  },
  {
    "name": "Продукт",
    "slug": "product",
    "description": "Управление продуктом и дизайн",
    "department": "Product",
    "position": "Product Manager",
    "level": "MIDDLE",
    "order": 4,
    "icon": "layers",
    "color": "#9C27B0"
  },
  {
    "name": "Продажи и Маркетинг",
    "slug": "sales-marketing",
    "description": "Руководства по продажам и маркетингу",
    "department": "Sales",
    "position": "Sales Representative",
    "level": "JUNIOR",
    "order": 5,
    "icon": "trending-up",
    "color": "#F44336"
  },
  {
    "name": "IT и Безопасность",
    "slug": "it-security",
    "description": "IT поддержка и политики безопасности",
    "department": "Engineering",
    "position": "DevOps Engineer",
    "level": "MIDDLE",
    "order": 6,
    "icon": "lock",
    "color": "#607D8B"
  }
]